kurdish_reshaper/__init__.py
kurdish_reshaper/__version__.py
kurdish_reshaper/kurdish_reshaper.py
kurdish_reshaper/letters.py
kurdish_reshaper/ligatures.py
kurdish_reshaper/reshaper_config.py
kurdish_reshaper-1.0.dist-info/METADATA
kurdish_reshaper-1.0.dist-info/WHEEL
kurdish_reshaper-1.0.dist-info/top_level.txt
kurdish_reshaper-1.0.dist-info/RECORD
