Metadata-Version: 2.1
Name: kurdish_reshaper
Version: 1.0
Requires-Dist: python-bidi
